prompt_sdk/__init__.py
prompt_sdk/config.py
prompt_sdk/main.py
prompt_sdk/models.py
prompt_sdk/templates/sdk_template.py.jinja
prompt_sdk/utils.py
prompt_sdk/validators.py
prompt_sdk_python-0.1.2.dist-info/METADATA
prompt_sdk_python-0.1.2.dist-info/WHEEL
prompt_sdk_python-0.1.2.dist-info/entry_points.txt
prompt_sdk_python-0.1.2.dist-info/licenses/LICENSE
prompt_sdk_python-0.1.2.dist-info/RECORD
