Metadata-Version: 2.4
Name: prompt-sdk-python
Version: 0.1.2
Summary: Generate client libraries from prompts.
Author-Email: Vincent Nahn <vincent@nahn.dev>
License-Expression: MIT
License-File: LICENSE
Requires-Python: >=3.10
Requires-Dist: jinja2>=3.1.6
Requires-Dist: pydantic>=2.12.5
Requires-Dist: pydantic-settings[toml]>=2.12.0
Requires-Dist: python-frontmatter>=1.1.0
Requires-Dist: typer>=0.20.0
